{
  "dataset": "phase8_repaired_2m_schnet_ab_subset",
  "rows": 30000,
  "seed": 42,
  "sampling": "proportional source_group x joint_bucket",
  "source_manifest": "D:\\\u6587\u6863\\molgap\\results\\phase8\\repaired_2m\\repaired_2m_manifest.parquet",
  "source_csv": "D:\\\u6587\u6863\\molgap\\data\\raw\\phase8_repaired_2m.csv",
  "output_csv": "D:\\\u6587\u6863\\molgap\\data\\raw\\phase8_repaired_2m_schnet_ab_30k.csv",
  "output_sha256": "5151298be9a48ed8ea83fa77110f051f661e8652ca54238b3ce2cfcd5ae637b7",
  "source_group_counts": {
    "aromatic_large": 36,
    "balanced": 55,
    "bridged_rigid": 199,
    "conjugated_da": 251,
    "exact2m_topup": 5900,
    "flexible_lowmid": 414,
    "general": 2242,
    "hetero_dense": 239,
    "high_gap": 46,
    "macro_amide": 221,
    "original_general": 5577,
    "rare": 4,
    "repair_v2": 6965,
    "sp3_nonaromatic": 55,
    "targeted": 7502,
    "topology_elements": 28,
    "very_large": 266
  },
  "joint_bucket_counts": {
    "gap_2_3|mw_350_500|arom_2_3|rot_5_9": 131,
    "gap_2_3|mw_350_500|arom_2_3|rot_ge10": 14,
    "gap_2_3|mw_350_500|arom_2_3|rot_lt5": 61,
    "gap_2_3|mw_350_500|arom_ge4|rot_5_9": 28,
    "gap_2_3|mw_350_500|arom_ge4|rot_lt5": 23,
    "gap_2_3|mw_350_500|arom_lt2|rot_5_9": 19,
    "gap_2_3|mw_350_500|arom_lt2|rot_ge10": 5,
    "gap_2_3|mw_350_500|arom_lt2|rot_lt5": 15,
    "gap_2_3|mw_500_700|arom_2_3|rot_5_9": 53,
    "gap_2_3|mw_500_700|arom_2_3|rot_ge10": 29,
    "gap_2_3|mw_500_700|arom_2_3|rot_lt5": 9,
    "gap_2_3|mw_500_700|arom_ge4|rot_5_9": 73,
    "gap_2_3|mw_500_700|arom_ge4|rot_ge10": 28,
    "gap_2_3|mw_500_700|arom_ge4|rot_lt5": 29,
    "gap_2_3|mw_500_700|arom_lt2|rot_5_9": 8,
    "gap_2_3|mw_500_700|arom_lt2|rot_ge10": 6,
    "gap_2_3|mw_500_700|arom_lt2|rot_lt5": 1,
    "gap_2_3|mw_ge700|arom_2_3|rot_5_9": 7,
    "gap_2_3|mw_ge700|arom_2_3|rot_ge10": 25,
    "gap_2_3|mw_ge700|arom_ge4|rot_5_9": 33,
    "gap_2_3|mw_ge700|arom_ge4|rot_ge10": 59,
    "gap_2_3|mw_ge700|arom_ge4|rot_lt5": 13,
    "gap_2_3|mw_ge700|arom_lt2|rot_5_9": 2,
    "gap_2_3|mw_ge700|arom_lt2|rot_ge10": 5,
    "gap_2_3|mw_lt350|arom_2_3|rot_5_9": 13,
    "gap_2_3|mw_lt350|arom_2_3|rot_lt5": 48,
    "gap_2_3|mw_lt350|arom_ge4|rot_lt5": 6,
    "gap_2_3|mw_lt350|arom_lt2|rot_5_9": 11,
    "gap_2_3|mw_lt350|arom_lt2|rot_lt5": 48,
    "gap_3_4|mw_350_500|arom_2_3|rot_5_9": 1551,
    "gap_3_4|mw_350_500|arom_2_3|rot_ge10": 132,
    "gap_3_4|mw_350_500|arom_2_3|rot_lt5": 460,
    "gap_3_4|mw_350_500|arom_ge4|rot_5_9": 651,
    "gap_3_4|mw_350_500|arom_ge4|rot_ge10": 21,
    "gap_3_4|mw_350_500|arom_ge4|rot_lt5": 355,
    "gap_3_4|mw_350_500|arom_lt2|rot_5_9": 113,
    "gap_3_4|mw_350_500|arom_lt2|rot_ge10": 27,
    "gap_3_4|mw_350_500|arom_lt2|rot_lt5": 48,
    "gap_3_4|mw_500_700|arom_2_3|rot_5_9": 397,
    "gap_3_4|mw_500_700|arom_2_3|rot_ge10": 219,
    "gap_3_4|mw_500_700|arom_2_3|rot_lt5": 35,
    "gap_3_4|mw_500_700|arom_ge4|rot_5_9": 597,
    "gap_3_4|mw_500_700|arom_ge4|rot_ge10": 212,
    "gap_3_4|mw_500_700|arom_ge4|rot_lt5": 131,
    "gap_3_4|mw_500_700|arom_lt2|rot_5_9": 20,
    "gap_3_4|mw_500_700|arom_lt2|rot_ge10": 26,
    "gap_3_4|mw_500_700|arom_lt2|rot_lt5": 5,
    "gap_3_4|mw_ge700|arom_2_3|rot_5_9": 14,
    "gap_3_4|mw_ge700|arom_2_3|rot_ge10": 71,
    "gap_3_4|mw_ge700|arom_ge4|rot_5_9": 151,
    "gap_3_4|mw_ge700|arom_ge4|rot_ge10": 180,
    "gap_3_4|mw_ge700|arom_ge4|rot_lt5": 21,
    "gap_3_4|mw_ge700|arom_lt2|rot_5_9": 4,
    "gap_3_4|mw_ge700|arom_lt2|rot_ge10": 18,
    "gap_3_4|mw_ge700|arom_lt2|rot_lt5": 2,
    "gap_3_4|mw_lt350|arom_2_3|rot_5_9": 208,
    "gap_3_4|mw_lt350|arom_2_3|rot_lt5": 628,
    "gap_3_4|mw_lt350|arom_ge4|rot_5_9": 5,
    "gap_3_4|mw_lt350|arom_ge4|rot_lt5": 114,
    "gap_3_4|mw_lt350|arom_lt2|rot_5_9": 121,
    "gap_3_4|mw_lt350|arom_lt2|rot_ge10": 8,
    "gap_3_4|mw_lt350|arom_lt2|rot_lt5": 213,
    "gap_4_6|mw_350_500|arom_2_3|rot_5_9": 4139,
    "gap_4_6|mw_350_500|arom_2_3|rot_ge10": 344,
    "gap_4_6|mw_350_500|arom_2_3|rot_lt5": 810,
    "gap_4_6|mw_350_500|arom_ge4|rot_5_9": 1299,
    "gap_4_6|mw_350_500|arom_ge4|rot_ge10": 66,
    "gap_4_6|mw_350_500|arom_ge4|rot_lt5": 473,
    "gap_4_6|mw_350_500|arom_lt2|rot_5_9": 514,
    "gap_4_6|mw_350_500|arom_lt2|rot_ge10": 200,
    "gap_4_6|mw_350_500|arom_lt2|rot_lt5": 138,
    "gap_4_6|mw_500_700|arom_2_3|rot_5_9": 836,
    "gap_4_6|mw_500_700|arom_2_3|rot_ge10": 721,
    "gap_4_6|mw_500_700|arom_2_3|rot_lt5": 74,
    "gap_4_6|mw_500_700|arom_ge4|rot_5_9": 609,
    "gap_4_6|mw_500_700|arom_ge4|rot_ge10": 379,
    "gap_4_6|mw_500_700|arom_ge4|rot_lt5": 67,
    "gap_4_6|mw_500_700|arom_lt2|rot_5_9": 89,
    "gap_4_6|mw_500_700|arom_lt2|rot_ge10": 188,
    "gap_4_6|mw_500_700|arom_lt2|rot_lt5": 17,
    "gap_4_6|mw_ge700|arom_2_3|rot_5_9": 74,
    "gap_4_6|mw_ge700|arom_2_3|rot_ge10": 461,
    "gap_4_6|mw_ge700|arom_2_3|rot_lt5": 2,
    "gap_4_6|mw_ge700|arom_ge4|rot_5_9": 74,
    "gap_4_6|mw_ge700|arom_ge4|rot_ge10": 457,
    "gap_4_6|mw_ge700|arom_ge4|rot_lt5": 9,
    "gap_4_6|mw_ge700|arom_lt2|rot_5_9": 30,
    "gap_4_6|mw_ge700|arom_lt2|rot_ge10": 194,
    "gap_4_6|mw_ge700|arom_lt2|rot_lt5": 1,
    "gap_4_6|mw_lt350|arom_2_3|rot_5_9": 1393,
    "gap_4_6|mw_lt350|arom_2_3|rot_ge10": 10,
    "gap_4_6|mw_lt350|arom_2_3|rot_lt5": 2803,
    "gap_4_6|mw_lt350|arom_ge4|rot_5_9": 17,
    "gap_4_6|mw_lt350|arom_ge4|rot_lt5": 202,
    "gap_4_6|mw_lt350|arom_lt2|rot_5_9": 1891,
    "gap_4_6|mw_lt350|arom_lt2|rot_ge10": 98,
    "gap_4_6|mw_lt350|arom_lt2|rot_lt5": 1851,
    "gap_6_8|mw_350_500|arom_2_3|rot_5_9": 10,
    "gap_6_8|mw_350_500|arom_2_3|rot_ge10": 3,
    "gap_6_8|mw_350_500|arom_lt2|rot_5_9": 62,
    "gap_6_8|mw_350_500|arom_lt2|rot_ge10": 79,
    "gap_6_8|mw_350_500|arom_lt2|rot_lt5": 17,
    "gap_6_8|mw_500_700|arom_2_3|rot_5_9": 1,
    "gap_6_8|mw_500_700|arom_2_3|rot_ge10": 5,
    "gap_6_8|mw_500_700|arom_lt2|rot_5_9": 21,
    "gap_6_8|mw_500_700|arom_lt2|rot_ge10": 62,
    "gap_6_8|mw_500_700|arom_lt2|rot_lt5": 3,
    "gap_6_8|mw_ge700|arom_2_3|rot_ge10": 3,
    "gap_6_8|mw_ge700|arom_lt2|rot_5_9": 4,
    "gap_6_8|mw_ge700|arom_lt2|rot_ge10": 53,
    "gap_6_8|mw_lt350|arom_2_3|rot_5_9": 13,
    "gap_6_8|mw_lt350|arom_2_3|rot_lt5": 15,
    "gap_6_8|mw_lt350|arom_lt2|rot_5_9": 785,
    "gap_6_8|mw_lt350|arom_lt2|rot_ge10": 104,
    "gap_6_8|mw_lt350|arom_lt2|rot_lt5": 566,
    "gap_ge8|mw_350_500|arom_lt2|rot_5_9": 2,
    "gap_ge8|mw_350_500|arom_lt2|rot_ge10": 4,
    "gap_ge8|mw_350_500|arom_lt2|rot_lt5": 1,
    "gap_ge8|mw_500_700|arom_lt2|rot_ge10": 3,
    "gap_ge8|mw_lt350|arom_lt2|rot_5_9": 20,
    "gap_ge8|mw_lt350|arom_lt2|rot_ge10": 13,
    "gap_ge8|mw_lt350|arom_lt2|rot_lt5": 18,
    "gap_lt2|mw_350_500|arom_2_3|rot_5_9": 4,
    "gap_lt2|mw_350_500|arom_2_3|rot_lt5": 6,
    "gap_lt2|mw_350_500|arom_ge4|rot_lt5": 1,
    "gap_lt2|mw_350_500|arom_lt2|rot_lt5": 1,
    "gap_lt2|mw_500_700|arom_2_3|rot_5_9": 3,
    "gap_lt2|mw_500_700|arom_2_3|rot_ge10": 2,
    "gap_lt2|mw_500_700|arom_ge4|rot_5_9": 2,
    "gap_lt2|mw_500_700|arom_ge4|rot_lt5": 2,
    "gap_lt2|mw_500_700|arom_lt2|rot_5_9": 1,
    "gap_lt2|mw_ge700|arom_2_3|rot_ge10": 2,
    "gap_lt2|mw_ge700|arom_ge4|rot_5_9": 4,
    "gap_lt2|mw_ge700|arom_ge4|rot_ge10": 4,
    "gap_lt2|mw_ge700|arom_ge4|rot_lt5": 3,
    "gap_lt2|mw_lt350|arom_2_3|rot_lt5": 3,
    "gap_lt2|mw_lt350|arom_lt2|rot_lt5": 5
  },
  "manifest_row_min": 20,
  "manifest_row_max": 1999962
}